ilit/__init__.py
ilit/benchmark.py
ilit/objective.py
ilit/pruning.py
ilit/quantization.py
ilit/version.py
ilit/adaptor/__init__.py
ilit/adaptor/adaptor.py
ilit/adaptor/mxnet.py
ilit/adaptor/pytorch.py
ilit/adaptor/tensorflow.py
ilit/adaptor/tf_utils/__init__.py
ilit/adaptor/tf_utils/graph_converter.py
ilit/adaptor/tf_utils/util.py
ilit/adaptor/tf_utils/graph_rewriter/__init__.py
ilit/adaptor/tf_utils/graph_rewriter/graph_base.py
ilit/adaptor/tf_utils/graph_rewriter/graph_info.py
ilit/adaptor/tf_utils/graph_rewriter/graph_util.py
ilit/adaptor/tf_utils/graph_rewriter/bf16/__init__.py
ilit/adaptor/tf_utils/graph_rewriter/bf16/bf16_convert.py
ilit/adaptor/tf_utils/graph_rewriter/generic/__init__.py
ilit/adaptor/tf_utils/graph_rewriter/generic/fold_batch_norm.py
ilit/adaptor/tf_utils/graph_rewriter/generic/fold_constant.py
ilit/adaptor/tf_utils/graph_rewriter/generic/fuse_column_wise_mul.py
ilit/adaptor/tf_utils/graph_rewriter/generic/fuse_pad_with_conv.py
ilit/adaptor/tf_utils/graph_rewriter/generic/graph_cse_optimizer.py
ilit/adaptor/tf_utils/graph_rewriter/generic/pre_optimize.py
ilit/adaptor/tf_utils/graph_rewriter/generic/remove_training_nodes.py
ilit/adaptor/tf_utils/graph_rewriter/generic/split_shared_input.py
ilit/adaptor/tf_utils/graph_rewriter/generic/strip_unused_nodes.py
ilit/adaptor/tf_utils/graph_rewriter/generic/update_enter.py
ilit/adaptor/tf_utils/graph_rewriter/int8/__init__.py
ilit/adaptor/tf_utils/graph_rewriter/int8/freeze_value.py
ilit/adaptor/tf_utils/graph_rewriter/int8/fuse_conv_requantize.py
ilit/adaptor/tf_utils/graph_rewriter/int8/fuse_matmul_requantize.py
ilit/adaptor/tf_utils/graph_rewriter/int8/insert_logging.py
ilit/adaptor/tf_utils/graph_rewriter/int8/scale_propagation.py
ilit/adaptor/tf_utils/quantize_graph/__init__.py
ilit/adaptor/tf_utils/quantize_graph/quantize_graph_base.py
ilit/adaptor/tf_utils/quantize_graph/quantize_graph_common.py
ilit/adaptor/tf_utils/quantize_graph/quantize_graph_concatv2.py
ilit-1.0.dist-info/LICENSE
ilit-1.0.dist-info/METADATA
ilit-1.0.dist-info/WHEEL
ilit-1.0.dist-info/entry_points.txt
ilit-1.0.dist-info/top_level.txt
ilit-1.0.dist-info/RECORD
